{
    "entities": [
        {
            "pos": [
                -0.6937878727912903,
                0.0650254487991333
            ],
            "type": 5
        },
        {
            "pos": [
                -0.04855310916900635,
                -0.2832356095314026
            ],
            "type": 5
        },
        {
            "pos": [
                0.8928595781326294,
                -0.0828847885131836
            ],
            "type": 5
        }
    ],
    "id": 97,
    "rooms": [
        87,
        98,
        -1,
        -1
    ]
}
